{
    "permissions": {
        "v1-users": {
            "permissions": ["PUT", "POST", "DELETE"]
        },
        "team": {
            "permissions": ["GET", "POST", "PUT"]
        },
        "v1-teams": {
            "permissions": ["DELETE"]
        }
    },
    "firms": {
        "id": 1,
        "deputies": [
            {
                "id": 77,
                "personType": "Deputy",
                "deputyStatus": "Inactive",
                "orders": [[]],
                "deputyNumber": 22,
                "organisationName": "pro dept",
                "deputySubType": []
            },
            {
                "id": 75,
                "personType": "Deputy",
                "deputyStatus": "Active",
                "orders": [[]],
                "eveningNumber": "07748933233",
                "deputyNumber": 20,
                "organisationName": "deputy pro",
                "organisationTeamOrDepartmentName": ""
            }
        ],
        "firmName": "Trustworthy Firm Inc",
        "addressLine1": "221 Baker Street",
        "addressLine2": "Covent Garden",
        "addressLine3": "",
        "town": "London",
        "county": "Buckinghamshire",
        "postcode": "B10 1FG",
        "phoneNumber": "333222111",
        "email": "trusty@firm.com",
        "firmNumber": 100004,
        "piiReceived": "20/12/2000",
        "piiExpiry": "01/12/2020",
        "piiAmount": 1000,
        "piiRequested": "15/11/2000"
    },
    "errors": [
        {
            "id": "pii-details",
            "validation_errors": {
                "piiReceived": {
                    "isEmpty": ""
                },
                "piiExpiry": {
                    "isEmpty": ""
                },
                "piiAmount": {
                    "isEmpty": ""
                }
            }
        },
        {
            "id": "request-pii-details",
            "validation_errors": {
                "piiRequested": {
                    "isEmpty": ""
                }
            }
        },
        {
            "id": "manage-firm-details-empty",
            "validation_errors": {
                "firmName": {
                    "isEmpty": ""
                }
            }
        },
        {
            "id": "manage-firm-details-too-long",
            "validation_errors": {
                "firmName": {
                    "stringLengthTooLong": ""
                }
            }
        }
    ],
    "successes": [
        {
            "id": "editPii"
        },
        {
            "id": "requestPii"
        },
        {
            "id": "manageFirm"
        }
    ]
}
